{"26": {"state": "suit", "block": 26, "track": "c", "difficulty": 3, "numFloors": 2, "savedBy": null, "becameSuitTime": 1667438915.150121}, "4": {"state": "suit", "block": 4, "track": "c", "difficulty": 3, "numFloors": 3, "savedBy": null, "becameSuitTime": 1667438753.4233122}, "6": {"state": "suit", "block": 6, "track": "l", "difficulty": 1, "numFloors": 2, "savedBy": null, "becameSuitTime": 1667438767.6485014}, "8": {"state": "suit", "block": 8, "track": "c", "difficulty": 2, "numFloors": 3, "savedBy": null, "becameSuitTime": 1667438729.6703355}, "9": {"state": "suit", "block": 9, "track": "c", "difficulty": 1, "numFloors": 1, "savedBy": null, "becameSuitTime": 1667438713.8352983}, "16": {"state": "suit", "block": 16, "track": "c", "difficulty": 2, "numFloors": 1, "savedBy": null, "becameSuitTime": 1667438680.9728386}}