{"4": {"state": "suit", "block": 4, "track": "l", "difficulty": 3, "numFloors": 3, "savedBy": null, "becameSuitTime": 1667438801.6036131}, "6": {"state": "suit", "block": 6, "track": "s", "difficulty": 2, "numFloors": 1, "savedBy": null, "becameSuitTime": 1667439078.0201848}, "9": {"state": "suit", "block": 9, "track": "l", "difficulty": 3, "numFloors": 3, "savedBy": null, "becameSuitTime": 1667438742.9348166}, "26": {"state": "suit", "block": 26, "track": "s", "difficulty": 1, "numFloors": 2, "savedBy": null, "becameSuitTime": 1667438880.283758}, "15": {"state": "suit", "block": 15, "track": "s", "difficulty": 3, "numFloors": 3, "savedBy": null, "becameSuitTime": 1667438878.4623501}}